docks/__init__.py
docks/__main__.py
docks/api.py
docks/cli.py
docks/client.py
docks/config.py
docks/datasets.py
docks/logging.py
docks/output.py
docks/commands/__init__.py
docks/commands/auth.py
docks/commands/datasets.py
docks/commands/images.py
docks/commands/report.py
docks/commands/runs.py
docks/commands/sandbox.py
docks/commands/tasks.py
docks/AGENTS.md
docks_cli-0.2.0.dist-info/METADATA
docks_cli-0.2.0.dist-info/WHEEL
docks_cli-0.2.0.dist-info/entry_points.txt
docks_cli-0.2.0.dist-info/RECORD
