Metadata-Version: 2.4
Name: docks-cli
Version: 0.2.0
Summary: CLI for managing Docks evaluation runs, datasets, and prebaked images
Project-URL: Homepage, https://thecontextlab.ai
Project-URL: Documentation, https://thecontextlab.ai/docs
Project-URL: Repository, https://github.com/thecontextlab/docks-cli
Author-email: Context Lab <dev@contextlab.io>
License-Expression: MIT
Keywords: cli,docks,evaluation,swe-bench
Classifier: Development Status :: 3 - Alpha
Classifier: Environment :: Console
Classifier: Intended Audience :: Developers
Classifier: License :: OSI Approved :: MIT License
Classifier: Programming Language :: Python :: 3
Classifier: Programming Language :: Python :: 3.11
Classifier: Programming Language :: Python :: 3.12
Requires-Python: >=3.11
Requires-Dist: httpx>=0.25.0
Requires-Dist: jsonschema>=4.0.0
Requires-Dist: keyring>=24.0.0
Requires-Dist: pydantic-settings>=2.0.0
Requires-Dist: pydantic>=2.0.0
Requires-Dist: pyyaml>=6.0.0
Requires-Dist: rich>=13.0.0
Requires-Dist: tomli-w>=1.0.0
Requires-Dist: tomli>=2.0.0; python_version < '3.11'
Requires-Dist: typer>=0.9.0
Provides-Extra: dev
Requires-Dist: pytest-asyncio>=0.21.0; extra == 'dev'
Requires-Dist: pytest>=7.0.0; extra == 'dev'
Requires-Dist: respx>=0.20.0; extra == 'dev'
Requires-Dist: ruff>=0.1.0; extra == 'dev'
Provides-Extra: minimal
